{
  "workflow": {
    "unique_name": "definition_workflow_01AT99AE0ZPCV4Q7l75DTusIEZcqIlB9jaH",
    "name": "Master",
    "title": "Master",
    "type": "generic.workflow",
    "base_type": "workflow",
    "variables": [
      {
        "schema_id": "datatype.string",
        "properties": {
          "value": "",
          "scope": "input",
          "name": "name",
          "type": "datatype.string",
          "is_required": false
        },
        "unique_name": "variable_workflow_01ATFXP4IJ3C33eXPTEZnjxRNKlNLUJRFJK",
        "object_type": "variable_workflow"
      }
    ],
    "properties": {
      "atomic": {
        "is_atomic": false
      },
      "delete_workflow_instance": false,
      "display_name": "Master",
      "runtime_user": {
        "override_target_runtime_user": false,
        "specify_on_workflow_start": false,
        "target_default": true
      },
      "target": {
        "target_type": "web-service.endpoint",
        "target_id": "definition_target_01AHHTT9L9VJ04ehSWxbXojgK3jfq8NFBeT",
        "execute_on_workflow_target": true
      }
    },
    "object_type": "definition_workflow",
    "categories": [
      "category_1BMfMXSnJMyt5Ihqi7rWJr5N8cf"
    ]
  },
  "targets": {
    "definition_target_01AHHTT9L9VJ04ehSWxbXojgK3jfq8NFBeT": {
      "unique_name": "definition_target_01AHHTT9L9VJ04ehSWxbXojgK3jfq8NFBeT",
      "name": "JSONPath Holder",
      "title": "JSONPath Holder",
      "type": "web-service.endpoint",
      "base_type": "target",
      "object_type": "definition_target",
      "properties": {
        "disable_certificate_validation": true,
        "display_name": "JSONPath Holder",
        "host": "jsonplaceholder.typicode.com",
        "no_runtime_user": true,
        "protocol": "https"
      }
    }
  }
}